converter/__init__.py
converter/src/__init__.py
converter/src/camel.py
converter/src/case.py
converter/src/custom.py
converter/src/customBetween.py
converter/src/flat.py
converter/src/kebab.py
converter/src/pascal.py
converter/src/path.py
converter/src/piped.py
converter/src/raw.py
converter/src/sentence.py
converter/src/snake.py
converter/src/title.py
tests/__init__.py
tests/main.py
super_case_converter_2000-1.1.2.dist-info/LICENSE
super_case_converter_2000-1.1.2.dist-info/LICENSE.txt
super_case_converter_2000-1.1.2.dist-info/METADATA
super_case_converter_2000-1.1.2.dist-info/WHEEL
super_case_converter_2000-1.1.2.dist-info/top_level.txt
super_case_converter_2000-1.1.2.dist-info/RECORD
