Metadata-Version: 2.1
Name: super-case-converter-2000
Version: 1.1.2
Summary: Case converter
Home-page: https://github.com/RiccardoCurcio/super-case-convertor-2000.git
Author: Riccardo Curcio
Author-email: curcioriccardo@gmail.com
License: GPL v3
Download-URL: https://github.com/RiccardoCurcio/super-case-convertor-2000/archive/v1.1.2.tar.gz
Keywords: snake,camel,pascal,kebab,flat,raw,path,piped,custom,title
Platform: UNKNOWN
Classifier: Programming Language :: Python :: 3
Classifier: License :: OSI Approved :: GNU General Public License v3 (GPLv3)
Classifier: Operating System :: OS Independent
Requires-Python: >=3.6
Requires-Dist: typing
